{
  "location": "ควนกลาง พิปูน นครศรีธรรมราช",
  "lat": 8.495,
  "lon": 99.652,
  "source": "Open-Meteo",
  "updated_at": "2026-05-17T18:49:46.513638+00:00",
  "forecast": [
    {
      "date": "2026-05-18",
      "date_label": "18/5 (จ.)",
      "temp_min": 23,
      "temp_max": 29,
      "humidity": 99,
      "rain_mm": 20.4,
      "rain_chance": 90,
      "wind_kmh": 11,
      "condition": "ฝนฟ้าคะนอง"
    },
    {
      "date": "2026-05-19",
      "date_label": "19/5 (อ.)",
      "temp_min": 24,
      "temp_max": 28,
      "humidity": 100,
      "rain_mm": 22.8,
      "rain_chance": 100,
      "wind_kmh": 12,
      "condition": "ฝนชุก"
    },
    {
      "date": "2026-05-20",
      "date_label": "20/5 (พ.)",
      "temp_min": 23,
      "temp_max": 29,
      "humidity": 99,
      "rain_mm": 24.5,
      "rain_chance": 100,
      "wind_kmh": 10,
      "condition": "ฝนชุก"
    },
    {
      "date": "2026-05-21",
      "date_label": "21/5 (พฤ.)",
      "temp_min": 24,
      "temp_max": 25,
      "humidity": 99,
      "rain_mm": 21.1,
      "rain_chance": 90,
      "wind_kmh": 9,
      "condition": "ฝนชุก"
    },
    {
      "date": "2026-05-22",
      "date_label": "22/5 (ศ.)",
      "temp_min": 24,
      "temp_max": 28,
      "humidity": 100,
      "rain_mm": 6.9,
      "rain_chance": 92,
      "wind_kmh": 9,
      "condition": "ฝนฟ้าคะนอง"
    },
    {
      "date": "2026-05-23",
      "date_label": "23/5 (ส.)",
      "temp_min": 24,
      "temp_max": 28,
      "humidity": 99,
      "rain_mm": 11.3,
      "rain_chance": 97,
      "wind_kmh": 10,
      "condition": "ฝนชุก"
    },
    {
      "date": "2026-05-24",
      "date_label": "24/5 (อา.)",
      "temp_min": 24,
      "temp_max": 28,
      "humidity": 99,
      "rain_mm": 13.2,
      "rain_chance": 91,
      "wind_kmh": 9,
      "condition": "ฝนชุก"
    }
  ]
}